TMC2209_PY/TMC2209.py
TMC2209_PY/__init__.py
TMC2209_PY/registers.py
TMC2209_PY/uart.py
tmc2209_py-0.1.4.dist-info/licenses/LICENSE
tmc2209_py-0.1.4.dist-info/METADATA
tmc2209_py-0.1.4.dist-info/WHEEL
tmc2209_py-0.1.4.dist-info/top_level.txt
tmc2209_py-0.1.4.dist-info/RECORD
