Metadata-Version: 2.4
Name: TMC2209_PY
Version: 0.1.4
Summary: A Python library for controlling the TMC2209 stepper motor driver
Home-page: https://github.com/bash227/TMC2209_Python
Author: Bashar Almadani
Author-email: basharalmadani88@gmail.com
License: MIT
Classifier: Programming Language :: Python :: 3
Classifier: License :: OSI Approved :: MIT License
Classifier: Operating System :: OS Independent
Requires-Python: >=3.6
License-File: LICENSE
Requires-Dist: pyserial
Dynamic: author
Dynamic: author-email
Dynamic: classifier
Dynamic: description
Dynamic: description-content-type
Dynamic: home-page
Dynamic: license
Dynamic: license-file
Dynamic: requires-dist
Dynamic: requires-python
Dynamic: summary
